datagrok_api/__init__.py
datagrok_api/datagrok_client.py
datagrok_api/http_client.py
datagrok_api/models/__init__.py
datagrok_api/models/data_connection.py
datagrok_api/models/func.py
datagrok_api/models/group.py
datagrok_api/models/model.py
datagrok_api/models/query.py
datagrok_api/models/script.py
datagrok_api/models/share_response.py
datagrok_api/models/user.py
datagrok_api/resources/__init__.py
datagrok_api/resources/connections.py
datagrok_api/resources/files.py
datagrok_api/resources/functions.py
datagrok_api/resources/groups.py
datagrok_api/resources/shares.py
datagrok_api/resources/tables.py
datagrok_api/resources/users.py
datagrok_api-0.0.8.dist-info/METADATA
datagrok_api-0.0.8.dist-info/WHEEL
datagrok_api-0.0.8.dist-info/RECORD
