Metadata-Version: 2.4
Name: datagrok-api
Version: 0.0.8
Summary: Client library for integration with datagrok API
Project-URL: Homepage, https://github.com/datagrok-ai/public
Project-URL: Issues, https://github.com/datagrok-ai/public/issues
Author-email: Andrew Skalkin <askalkin@datagrok.ai>, Amelichev Konstantin <kamelichev@datagrok.ai>
Classifier: License :: OSI Approved :: MIT License
Classifier: Operating System :: OS Independent
Classifier: Programming Language :: Python :: 3
Requires-Python: >=3.8
Requires-Dist: pandas
Requires-Dist: requests
Requires-Dist: requests-toolbelt
Provides-Extra: test
Requires-Dist: data-to-xml; extra == 'test'
Requires-Dist: pytest; extra == 'test'
Requires-Dist: pytest-item-dict; extra == 'test'
Requires-Dist: pytest-xml; extra == 'test'
Requires-Dist: requests-mock; extra == 'test'
